craft/__init__.py
craft/craft.py
craft/craft_env.py
language_feedback-0.0.1.dist-info/METADATA
language_feedback-0.0.1.dist-info/WHEEL
language_feedback-0.0.1.dist-info/top_level.txt
language_feedback-0.0.1.dist-info/RECORD
